kmApi/__init__.py
kmApi/apiTool.py
kmapitool-1.0.4.dist-info/METADATA
kmapitool-1.0.4.dist-info/WHEEL
kmapitool-1.0.4.dist-info/top_level.txt
kmapitool-1.0.4.dist-info/RECORD
