Metadata-Version: 2.1
Name: kmapitool
Version: 1.0.4
Summary: km api tool
Home-page: UNKNOWN
Author: xiaolong.huang
Author-email: xiaolonghuang@emotibot.com
License: UNKNOWN
Platform: UNKNOWN
Requires-Dist: requests (==2.28.2)
